[
    {
        "key": "dbln",
        "value": "%7B%2261578781763918%22%3A%22lX9C2aXQ%22%2C%2261578877957883%22%3A%2255LIWTXd%22%7D",
        "domain": "facebook.com",
        "path": "/login/device-based/",
        "hostOnly": false,
        "creation": "2025-08-02T15:44:37.510Z",
        "lastAccessed": "2025-08-02T15:44:37.515Z"
    },
    {
        "key": "datr",
        "value": "jCWOaPgk8AcvDr0ucgM-zJu9",
        "domain": "facebook.com",
        "path": "/",
        "hostOnly": false,
        "creation": "2025-08-02T15:44:37.516Z",
        "lastAccessed": "2025-08-02T15:44:37.516Z"
    },
    {
        "key": "sb",
        "value": "jCWOaK2RP3kTCg4if3LfXMRt",
        "domain": "facebook.com",
        "path": "/",
        "hostOnly": false,
        "creation": "2025-08-02T15:44:37.516Z",
        "lastAccessed": "2025-08-02T15:44:37.516Z"
    },
    {
        "key": "ps_l",
        "value": "1",
        "domain": "facebook.com",
        "path": "/",
        "hostOnly": false,
        "creation": "2025-08-02T15:44:37.516Z",
        "lastAccessed": "2025-08-02T15:44:37.516Z"
    },
    {
        "key": "ps_n",
        "value": "1",
        "domain": "facebook.com",
        "path": "/",
        "hostOnly": false,
        "creation": "2025-08-02T15:44:37.516Z",
        "lastAccessed": "2025-08-02T15:44:37.516Z"
    },
    {
        "key": "vpd",
        "value": "v1%3B646x360x2",
        "domain": "facebook.com",
        "path": "/",
        "hostOnly": false,
        "creation": "2025-08-02T15:44:37.516Z",
        "lastAccessed": "2025-08-02T15:44:37.516Z"
    },
    {
        "key": "dpr",
        "value": "2",
        "domain": "facebook.com",
        "path": "/",
        "hostOnly": false,
        "creation": "2025-08-02T15:44:37.516Z",
        "lastAccessed": "2025-08-02T15:44:37.516Z"
    },
    {
        "key": "c_user",
        "value": "61578877957883",
        "domain": "facebook.com",
        "path": "/",
        "hostOnly": false,
        "creation": "2025-08-02T15:44:37.516Z",
        "lastAccessed": "2025-08-02T15:44:37.516Z"
    },
    {
        "key": "xs",
        "value": "18%3AnFW_XxozBF9aGQ%3A2%3A1754149174%3A-1%3A-1",
        "domain": "facebook.com",
        "path": "/",
        "hostOnly": false,
        "creation": "2025-08-02T15:44:37.516Z",
        "lastAccessed": "2025-08-02T15:44:37.516Z"
    },
    {
        "key": "locale",
        "value": "en_US",
        "domain": "facebook.com",
        "path": "/",
        "hostOnly": false,
        "creation": "2025-08-02T15:44:37.516Z",
        "lastAccessed": "2025-08-02T15:44:37.516Z"
    },
    {
        "key": "pas",
        "value": "61578781763918%3AJdUFJPmayk%2C61578877957883%3A58XGrwCPdf",
        "domain": "facebook.com",
        "path": "/",
        "hostOnly": false,
        "creation": "2025-08-02T15:44:37.516Z",
        "lastAccessed": "2025-08-02T15:44:37.516Z"
    },
    {
        "key": "m_pixel_ratio",
        "value": "2",
        "domain": "facebook.com",
        "path": "/",
        "hostOnly": false,
        "creation": "2025-08-02T15:44:37.516Z",
        "lastAccessed": "2025-08-02T15:44:37.516Z"
    },
    {
        "key": "wd",
        "value": "360x772",
        "domain": "facebook.com",
        "path": "/",
        "hostOnly": false,
        "creation": "2025-08-02T15:44:37.516Z",
        "lastAccessed": "2025-08-02T15:44:37.516Z"
    },
    {
        "key": "fr",
        "value": "09Uexnqshc0Er9DKY.AWfzwlDdSk-BaJYnGrTP8vcEjN9-oplGRt-2gzSz7IpfhA0yBAU.BojiWM..AAA.0.0.BojjGG.AWfOd_9Y1zeLcSWWyuPWcwG15D8",
        "domain": "facebook.com",
        "path": "/",
        "hostOnly": false,
        "creation": "2025-08-02T15:44:37.516Z",
        "lastAccessed": "2025-08-02T15:44:37.516Z"
    },
    {
        "key": "wl_cbv",
        "value": "v2%3Bclient_version%3A2884%3Btimestamp%3A1754149254",
        "domain": "facebook.com",
        "path": "/",
        "hostOnly": false,
        "creation": "2025-08-02T15:44:37.516Z",
        "lastAccessed": "2025-08-02T15:44:37.516Z"
    },
    {
        "key": "fbl_st",
        "value": "100436764%3BT%3A29235820",
        "domain": "facebook.com",
        "path": "/",
        "hostOnly": false,
        "creation": "2025-08-02T15:44:37.516Z",
        "lastAccessed": "2025-08-02T15:44:37.516Z"
    }
        ]
